{
  "name": "Austin Bishop",
  "age": 44,
  "address": {
    "street": "Vubwu Pass",
    "city": "Kulvewzo",
    "state": "LA",
    "zip": "81193"
  },
  "contact": {
    "phone": "(717) 784-8208",
    "servicePhone": "800814573"
  },
  "birthday": "2003-06-15T17:00:32.206Z",
  "ip": "246.32.112.244",
  "foo": "bar",
  "profile": {
    "about": "Ca gonsa ipmugsuj zenin hohamo veder oh ulro fi ok aclud fo rikoce evda uso umvi odesgo. Les ev wuve zeda winjev kakas ho vizimuk bop uworaf bamikis te. Cor dor neh nebew geh kopunuh kotfakum kok zez no wosho si ca giduwo nadarri. Ava masis hognagrah siiv beg abosu ga ufafalsu vumoreg reh dujumew ihites toceso vo ita emha. Cov viw ore otoga harati wawok afviki mej ve dafca enala acgo. Ki isolu futej efuiwji fo etsoma ac tajfudu esa na wa hutjoute.",
    "bio": "Bukarwo jigma pedadic sukafi ravekdom iluwa gi mu mesbiw wuwas ke dadtuwta pun voraro zovat mofujos hif. Faw boke fefip gashi dotgujem ne ota rah lacsuwapi du pamri oviri rovu ha. Gupiki lo sapi fosle mukoh do cav iceho obi wuguic dijsafce igo lid ruded tuz enpubwu. Beghonhit imtugas tolsu cogunjab ji hokkis liw pergi ulo was hinit done uci."
  },
  "apiKey": "32f66596d625850e466e8ca14f2dfdd8c1a2177988616d8070873f0b572cbbb1",
  "currency": {
    "code": "IRR",
    "name": "Iran Rial"
  }
}