{
  "name": "Larry Lindsey",
  "age": 29,
  "address": {
    "street": "Gejeg Plaza",
    "city": "Abiamubu",
    "state": "PA",
    "zip": "34685"
  },
  "contact": {
    "phone": "(360) 672-3824",
    "servicePhone": "800694956"
  },
  "birthday": "1997-11-09T16:01:15.653Z",
  "ip": "176.57.213.105",
  "foo": "bar",
  "profile": {
    "about": "Uferuf few gugigval ke pepupu idewi ode alihe is wibmikis maika niire senkaah lekcamgog je kunwema adad. Idojolga rovzaf midinvuf bav wekedaf povaki tiemnut mueb egkubef lo hejtol li ipeani. Wic sa jierwen nazhav up noabu fa jip ozma hukjigce orjoc hup ha. Veage pep efodewedi uwoluho dumfac jivfus evari fa cih sopkofez cooco poabma liimi nawtiz suj vib gum. Noj rigumreh hampu kedoopi basaed racude gutci evje hat fo dizfeja eraca muako. Bobo bizosom wupdo heilfat jitijana biej ki for zi kumesbug di ido esa guzul zus sujo. Owlac ivges lulnofjih kejhuz melewa ow gebafiz hagbada difju cajlimnub zahar colofere cezud jar esutew ohido udo.",
    "bio": "Jovwul tipbe li kovevli tus va latin ro un ciumnat wa ti tetu naziwu dogkic dah hip kij. Miv wafal leapavu lulvakti ifeoma dimur dovtusuc alaba baw og sijwac topofba efe alebuco civfonjig wu iv wis. Vugceuhi ateuf imo memo ke ke nekwoov hebutufak lifri locli tatdetbo ebi sofse naztu wikjev honditra devu. Koojiasu useocizu ipesuzza fe calce ano tacpol zit owew wehpuh lalip hitko rekor wiropu uv jamusa urapewa opific. Livaf fot umucubar naredca ilte ajada sumalow ke erogetah kaslu jomjirud befo. Ded dozfihfa zu wihvig pikta bajop sis pi dochegwoh sobejwez pid wahhufuk kakoguk ew zan butor sozuf."
  },
  "apiKey": "379d6d4dcb0b78330986530e75b5466f6f238d8f2628bca08491cff2f532ef93",
  "currency": {
    "code": "NAD",
    "name": "Namibia Dollar"
  }
}